cloudflare_images/__init__.py
cloudflare_images/main.py
cloudflare_images-0.1.8.dist-info/LICENSE
cloudflare_images-0.1.8.dist-info/METADATA
cloudflare_images-0.1.8.dist-info/WHEEL
cloudflare_images-0.1.8.dist-info/top_level.txt
cloudflare_images-0.1.8.dist-info/RECORD
