Metadata-Version: 2.1
Name: cloudflare-images
Version: 0.1.8
Summary: Wrapper around Cloudflare Images API
Author-email: Marcelino Veloso III <hi@mv3.dev>
Requires-Python: >=3.11
License-File: LICENSE
Requires-Dist: start-cloudflare >=0.0.5
Requires-Dist: httpx >=0.24
Provides-Extra: dev
Requires-Dist: rich >=13.3 ; extra == 'dev'
Requires-Dist: pytest >=8.3 ; extra == 'dev'
Requires-Dist: pytest-cov >=4.1 ; extra == 'dev'
Requires-Dist: build >=1.0.3 ; extra == 'dev'
Requires-Dist: twine >=4.0.2 ; extra == 'dev'
